{
    "Rect1":{
        
   
    "Link1":{
        "type": "ellipse",
        "cx": "150", 
        "cy": "120", 
        "rx": "110", 
        "ry": "30",
        "fill":"white",
        "class":"taskClose",
        "id": "Link1"
    },
    "Link2":{
        "type":"ellipse",
        "cx": "180",
        "cy": "200",
        "rx": "110",
        "ry":"30",
        "fill": "white",
        "class":"taskClose",
        "id":"Link2"
    },
    "Link3":{
        "type":"ellipse",
        "cx": "380",
        "cy": "620",
        "rx": "110",
        "ry":"30",
        "fill": "white",
        "class":"taskClose",
        "id":"Link3"
    },
    "Link4":{
        "type":"ellipse",
        "cx": "180",
        "cy": "320",
        "rx": "110",
        "ry":"30",
        "fill": "white",
        "class":"taskClose",
        "id":"Link4"
    },
    "Link5":{
        "type":"ellipse",
        "cx": "480",
        "cy": "120",
        "rx": "110",
        "ry":"30",
        "fill": "white",
        "class":"taskClose",
        "id":"Link5"
    },
    
    "Link6":{
        "type":"ellipse",
        "cx": "80",
        "cy": "520",
        "rx": "110",
        "ry":"30",
        "fill": "white",
        "class":"taskClose",
        "id":"Link6"
    },
    
    "Link7":{
        "type":"ellipse",
        "cx": "400",
        "cy": "480",
        "rx": "110",
        "ry":"30",
        "fill": "white",
        "class":"taskClose",
        "id":"Link7"
    },
    
    "Link8":{
        "type":"ellipse",
        "cx": "580",
        "cy": "220",
        "rx": "110",
        "ry":"30",
        "fill": "white",
        "class":"taskClose",
        "id":"Link8"
    },
    
    "Link9":{
        "type":"ellipse",
        "cx": "380",
        "cy": "620",
        "rx": "110",
        "ry":"30",
        "fill": "white",
        "class":"taskClose",
        "id":"Link9"
    },
    "Link10":{
        "type":"ellipse",
        "cx": "380",
        "cy": "340",
        "rx": "110",
        "ry":"30",
        "fill": "white",
        "class":"taskClose",
        "id":"Link10"
    },
    
    "Link11":{
        "type":"ellipse",
        "cx": "80",
        "cy": "620",
        "rx": "110",
        "ry":"30",
        "fill": "white",
        "class":"taskClose",
        "id":"Link11"
    },
    
    "Link12":{
        "type":"ellipse",
        "cx": "630",
        "cy": "620",
        "rx": "110",
        "ry":"30",
        "fill": "white",
        "class":"taskClose",
        "id":"Link12"
    },
    
    "Link13":{
        "type":"ellipse",
        "cx": "480",
        "cy": "400",
        "rx": "110",
        "ry":"30",
        "fill": "white",
        "class":"taskClose",
        "id":"Link13"
    },
    
    "Link14":{
        "type":"ellipse",
        "cx": "260",
        "cy": "420",
        "rx": "110",
        "ry":"30",
        "fill": "white",
        "class":"taskClose",
        "id":"Link14"
    },
    
    "Link15":{
        "type":"ellipse",
        "cx": "730",
        "cy": "350",
        "rx": "110",
        "ry":"30",
        "fill": "white",
        "class":"taskClose",
        "id":"Link15"
    },
    
    "Link16":{
        "type":"ellipse",
        "cx": "680",
        "cy": "500",
        "rx": "110",
        "ry":"30",
        "fill": "white",
        "class":"taskClose",
        "id":"Link16"
    },
        "but":{
        "type": "image",
        "x": "750",
        "y": "30",
        "width": "40",
        "height": "40",
        "color": "#11111",
        "href": "/static/xblock/resources/infosecurexblock.infosecurexblock/public/images/question.svg",
        "id": "task"
        },
            "FileText":{
                "type":"text",
                "x": "177",
                "y": "50",
                "fontSize":"10",
                "fontFamily":"SegoeUI",
                "fill": "black",
                "id":"File1TextID"
            },
            "taskDiv":{
                "type": "rect",
                "x": "150", 
                "y": "30", 
                "width": "750", 
                "height": "750", 
                "fill": "#f3faffef",
                "stroke":"#0075b4",
                "id": "taskId"
            },
            "taskText":{
                "type":"text",
                "x": "170",
                "y": "50",
                "fontSize":"20",
                "fontFamily":"SegoeUI",
                "fill": "black",
                "id":"taskTextID"
            },
            "arrow":{
                "type": "image",
                "x": "165",
                "y": "40",
                "width": "20",
                "height": "20",
                "href": "/static/xblock/resources/infosecurexblock.infosecurexblock/public/images/arrow.svg",
                "id": "arrowid"
                }
},
"Rect3":{
    "linka1":{"type":"text", 
        "idnum":"star", 
        "id": "link1", 
        "class": "taskClose link1", 
        "value":"<text x='80' y='120' id ='link1' color:blue class='taskClose' >http://google.com</text>" 
        },
        "linka2":{"type":"text", 
            "idnum":"star", 
            "id": "link2", 
            "class": "taskClose link2", 
            "value":"<text x='80' y='200' id ='link2' class='taskClose' >https://bank.ex.com</text>" 
            },
            "linka3":{"type":"text", 
                "idnum":"star", 
                "id": "link3", 
                "class": "taskClose link3", 
                "value":"<text x='310' y='620' id ='link3' class='taskClose' >http://gogle.com</text>" 
                },
                "linka4":{"type":"text", 
                    "idnum":"star", 
                    "id": "link4", 
                    "class": "taskClose link4", 
                    "value":"<text x='90' y='320' id ='link4' class='taskClose' >http://media.ls.urfu.ru</text>" 
                    },
                    "linka5":{"type":"text", 
                        "idnum":"star", 
                        "id": "link5", 
                        "class": "taskClose link5", 
                        "value":"<text x='380' y='120' id ='link5' class='taskClose' >http://ru.wikipedia.org</text>" 
                        },
                        "linka6":{"type":"text", 
                            "idnum":"star", 
                            "id": "link6", 
                            "class": "taskClose link6", 
                            "value":"<text x='10' y='520' id ='link6' class='taskClose' >https://urfu.ru.u</text>" 
                            },
                            "linka7":{"type":"text", 
                                "idnum":"star", 
                                "id": "link7", 
                                "class": "taskClose link7", 
                                "value":"<text x='290' y='480' id ='link7' class='taskClose' >http://traficonverter.biz</text>" 
                                },
                                "linka8":{"type":"text", 
                                    "idnum":"star", 
                                    "id": "link8", 
                                    "class": "taskClose link8", 
                                    "value":"<text x='510' y='220' id ='link8' class='taskClose' >https://vk.com</text>" 
                                    },
                                    "linka9":{"type":"text", 
                                        "idnum":"star", 
                                        "id": "link9", 
                                        "class": "taskClose link9", 
                                        "value":"<text x='310' y='620' id ='link9' class='taskClose' >https://alfabank.ru</text>" 
                                        },
                                        "linka10":{"type":"text", 
                                            "idnum":"star", 
                                            "id": "link10", 
                                            "class": "taskClose link10", 
                                            "value":"<text x='300' y='340' id ='link10' class='taskClose' >http://vk.my.page.bl</text>" 
                                            },
                                            "linka11":{"type":"text", 
                                                "idnum":"star", 
                                                "id": "link11", 
                                                "class": "taskClose link11", 
                                                "value":"<text x='10' y='620' id ='link11' class='taskClose' >https://intuit.ru</text>" 
                                                },
                                                "linka12":{"type":"text", 
                                                    "idnum":"star", 
                                                    "id": "link12", 
                                                    "class": "taskClose link12", 
                                                    "value":"<text x='550' y='620' id ='link12' class='taskClose' >https://facebok.com</text>" 
                                                    },
                                                    "linka13":{"type":"text", 
                                                        "idnum":"star", 
                                                        "id": "link13", 
                                                        "class": "taskClose link13", 
                                                        "value":"<text x='410' y='400' id ='link13' class='taskClose' >https://yandex.ru</text>" 
                                                        },
                                                        "linka14":{"type":"text", 
                                                            "idnum":"star", 
                                                            "id": "link14", 
                                                            "class": "taskClose link14", 
                                                            "value":"<text x='190' y='420' id ='link14' class='taskClose' >https://e1.ru</text>" 
                                                            },
                                                            "linka15":{"type":"text", 
                                                                "idnum":"star", 
                                                                "id": "link15", 
                                                                "class": "taskClose link15", 
                                                                "value":"<text x='660' y='350' id ='link15' class='taskClose' >https://pogoda.ru</text>" 
                                                                },
                                                                "linka16":{"type":"text", 
                                                                    "idnum":"star", 
                                                                    "id": "link16", 
                                                                    "class": "taskClose link16", 
                                                                    "value":"<text x='610' y='500' id ='link16' class='taskClose' >https://news.com</text>" 
                                                                    }}
}